MANIFEST.in
README.md
VERSION
requirements.txt
setup.cfg
setup.py
proxy_check/__init__.py
proxy_check/__main__.py
proxy_check/logger.py
proxy_check.egg-info/PKG-INFO
proxy_check.egg-info/SOURCES.txt
proxy_check.egg-info/dependency_links.txt
proxy_check.egg-info/requires.txt
proxy_check.egg-info/top_level.txt